xm2xl/__init__.py
xm2xl/xm2xl.py
xm2xl-0.2.1.dist-info/METADATA
xm2xl-0.2.1.dist-info/WHEEL
xm2xl-0.2.1.dist-info/entry_points.txt
xm2xl-0.2.1.dist-info/licenses/LICENSE
xm2xl-0.2.1.dist-info/RECORD
